{"type": "Feature", "id": 12513477, "properties": {"woe:id": 12513477, "woe:parent_id": 1042772, "woe:name": "Bandara Udara Internasional Airport", "woe:placetype": 14, "woe:placetype_name": "Airport", "woe:lang": "UNK", "iso:country": "ID", "meta:provider": ["geoplanet:7.3.1", "geoplanet:7.3.2", "geoplanet:7.4.0", "geoplanet:7.4.1", "geoplanet:7.5.1", "geoplanet:7.5.2", "geoplanet:7.6.0", "geoplanet:7.8.1", "geoplanet:7.9.0", "geoplanet:7.10.0", "geoplanet:8.0.0", "woeplanet:8.0.0"], "meta:indexed": "2020-08-20T20:48:45.179961", "woe:alias_UNK_V": ["Bandara Udara Int'l Airport", "Bandara Udara Internasional"], "woe:alias_ENG_V": ["SUB Airport", "SUB", "Juanda International"], "meta:updated": "2020-08-22T01:54:14.558702", "woe:alias_ENG_P": ["Juanda International Airport"], "woe:hierarchy": {"continent": 24865671, "country": 23424846, "town": 0, "planet": 1, "county": 56000380, "suburb": 0, "state": 2345717, "region": 0, "localadmin": 0}, "woe:timezone_id": 28350830, "woe:hash": "qw8nn9ct424n", "woe:centroid": [112.787804, -7.37234], "geom:latitude": -7.37234, "geom:longitude": 112.787804, "geom:hash": "qw8nn9ct424n", "woe:latitude": -7.37234, "geom:centroid": [112.787804, -7.37234], "woe:longitude": 112.787804, "woe:repo": "woeplanet-airport-id"}, "geometry": {"coordinates": [112.787804, -7.37234], "type": "Point"}}