{"type": "Feature", "id": 12513489, "properties": {"woe:id": 12513489, "woe:parent_id": 1031110, "woe:name": "Padangkemiling Airport", "woe:placetype": 14, "woe:placetype_name": "Airport", "woe:lang": "ENG", "iso:country": "ID", "meta:provider": ["geoplanet:7.3.1", "geoplanet:7.3.2", "geoplanet:7.4.0", "geoplanet:7.4.1", "geoplanet:7.5.1", "geoplanet:7.5.2", "geoplanet:7.6.0", "geoplanet:7.8.1", "geoplanet:7.9.0", "geoplanet:7.10.0", "geoplanet:8.0.0", "woeplanet:8.0.0"], "meta:indexed": "2020-08-20T20:48:45.190308", "woe:alias_ENG_V": ["BKS Airport", "BKS"], "meta:updated": "2020-08-22T01:54:14.563801", "woe:hierarchy": {"continent": 24865671, "country": 23424846, "town": 0, "planet": 1, "county": 56000342, "suburb": 0, "state": 2345712, "region": 0, "localadmin": 0}, "woe:timezone_id": 28350830, "woe:hash": "qr2f0b9q8usm", "woe:centroid": [102.339401, -3.8633], "geom:latitude": -3.8633, "geom:longitude": 102.339401, "geom:hash": "qr2f0b9q8usm", "woe:latitude": -3.8633, "geom:centroid": [102.339401, -3.8633], "woe:longitude": 102.339401, "woe:repo": "woeplanet-airport-id"}, "geometry": {"coordinates": [102.339401, -3.8633], "type": "Point"}}