{"type": "Feature", "id": 12513450, "geometry": {"type": "Point", "coordinates": [110.751404, -7.5181]}, "properties": {"woe:id": 12513450, "woe:parent_id": 1032287, "woe:name": "Adi Sumarmo Wiryokusumo Airport", "woe:placetype": 14, "woe:placetype_name": "Airport", "woe:lang": "ENG", "iso:country": "ID", "meta:provider": ["geoplanet:7.3.1", "geoplanet:7.3.2", "geoplanet:7.4.0", "geoplanet:7.4.1", "geoplanet:7.5.1", "geoplanet:7.5.2", "geoplanet:7.6.0", "geoplanet:7.8.1", "geoplanet:7.9.0", "geoplanet:7.10.0", "geoplanet:8.0.0", "woeplanet:8.0.0"], "meta:indexed": "2020-08-20T20:48:45.157564", "woe:alias_ENG_V": ["SOC Airport", "SOC", "Adi Sumarmo Wiryokusumo"], "meta:updated": "2020-10-14T11:59:23.975162", "woe:hierarchy": {"continent": 24865671, "country": 23424846, "town": 0, "planet": 1, "county": 56000336, "suburb": 0, "state": 2345716, "region": 0, "localadmin": 0}, "woe:timezone_id": 28350830, "woe:hash": "qqwv0pqeyu86", "woe:centroid": [110.751404, -7.5181], "geom:latitude": -7.5181, "geom:longitude": 110.751404, "geom:hash": "qqwv0pqeyu86", "woe:latitude": -7.5181, "geom:centroid": [110.751404, -7.5181], "woe:longitude": 110.751404, "woe:repo": "woeplanet-airport-id", "geom:area": 0.0, "woe:scale": 19}}