{"type": "Feature", "id": 12513479, "geometry": {"type": "Point", "coordinates": [97.2556, 5.0689]}, "properties": {"woe:id": 12513479, "woe:parent_id": 1038173, "woe:name": "Lhok Sukon Airport", "woe:placetype": 14, "woe:placetype_name": "Airport", "woe:lang": "ENG", "iso:country": "ID", "meta:provider": ["geoplanet:7.3.1", "geoplanet:7.3.2", "geoplanet:7.4.0", "geoplanet:7.4.1", "geoplanet:7.5.1", "geoplanet:7.5.2", "geoplanet:7.6.0", "geoplanet:7.8.1", "geoplanet:7.9.0", "geoplanet:7.10.0", "geoplanet:8.0.0", "woeplanet:8.0.0"], "meta:indexed": "2020-08-20T20:48:45.181745", "meta:updated": "2020-10-14T11:59:23.978603", "woe:hierarchy": {"continent": 24865671, "country": 23424846, "town": 0, "planet": 1, "county": 56000307, "suburb": 0, "state": 2345710, "region": 0, "localadmin": 0}, "woe:timezone_id": 28350830, "woe:hash": "w0vhv4g27xrq", "woe:centroid": [97.2556, 5.0689], "geom:latitude": 5.0689, "geom:longitude": 97.2556, "geom:hash": "w0vhv4g27xrq", "woe:latitude": 5.0689, "geom:centroid": [97.2556, 5.0689], "woe:longitude": 97.2556, "woe:repo": "woeplanet-airport-id", "geom:area": 0.0, "woe:scale": 19}}